streamlit_embeded/__init__.py
streamlit_embeded/version.py
streamlit_embeded/frontend/build/asset-manifest.json
streamlit_embeded/frontend/build/index.html
streamlit_embeded/frontend/build/static/js/2.c6a75a21.chunk.js
streamlit_embeded/frontend/build/static/js/2.c6a75a21.chunk.js.LICENSE.txt
streamlit_embeded/frontend/build/static/js/main.c2d02156.chunk.js
streamlit_embeded/frontend/build/static/js/runtime-main.fb63973a.js
streamlit_embeded-0.0.1.dist-info/LICENSE
streamlit_embeded-0.0.1.dist-info/METADATA
streamlit_embeded-0.0.1.dist-info/WHEEL
streamlit_embeded-0.0.1.dist-info/top_level.txt
streamlit_embeded-0.0.1.dist-info/RECORD
