Metadata-Version: 2.1
Name: streamlit-embeded
Version: 0.0.1
Summary: Common embeded for Streamlit.
Home-page: https://github.com/mapix/streamlit-embeded
Author: mapix
License: MIT
Platform: UNKNOWN
Requires-Python: >=3.6
